telegram_alert_bot/__init__.py
telegram_alert_bot/bot.py
telegram_alert_bot-0.2.1.dist-info/METADATA
telegram_alert_bot-0.2.1.dist-info/WHEEL
telegram_alert_bot-0.2.1.dist-info/licenses/LICENSE
telegram_alert_bot-0.2.1.dist-info/RECORD
