Metadata-Version: 2.3
Name: telegram-alert-bot
Version: 0.2.1
Summary: An asynchronous Telegram bot designed for sending alerts and notifications with a message queuing system.
Project-URL: Homepage, https://github.com/pudjojotaro/telegram-alert-bot
Author: https://github.com/pudjojotaro
Classifier: License :: OSI Approved :: MIT License
Classifier: Operating System :: OS Independent
Classifier: Programming Language :: Python :: 3
Requires-Python: >=3.7
Requires-Dist: python-telegram-bot>=20.0
